[
  {
    "Negeri": "KEDAH",
    "Jumlah": 1585085,
    "Polis": 6842,
    "Tentera": 8454,
    "UndiBiasa": 1569624,
    "PTH": 165
  },
  {
    "Negeri": "KELANTAN",
    "Jumlah": 1411912,
    "Polis": 5030,
    "Tentera": 6175,
    "UndiBiasa": 1400570,
    "PTH": 137
  },
  {
    "Negeri": "TERENGGANU",
    "Jumlah": 930894,
    "Polis": 4513,
    "Tentera": 2444,
    "UndiBiasa": 923857,
    "PTH": 80
  },
  {
    "Negeri": "PULAU PINANG",
    "Jumlah": 1234198,
    "Polis": 6451,
    "Tentera": 4843,
    "UndiBiasa": 1222710,
    "PTH": 194
  },
  {
    "Negeri": "SELANGOR",
    "Jumlah": 3747057,
    "Polis": 18557,
    "Tentera": 8000,
    "UndiBiasa": 3719495,
    "PTH": 1005
  },
  {
    "Negeri": "NEGERI SEMBILAN",
    "Jumlah": 864425,
    "Polis": 6335,
    "Tentera": 19744,
    "UndiBiasa": 838200,
    "PTH": 146
  }
]